ai/backend/krunner/static_gnu/__init__.py
ai/backend/krunner/static_gnu/krunner-env.static-gnu.aarch64.tar.xz
ai/backend/krunner/static_gnu/krunner-python.static-gnu.txt
ai/backend/krunner/static_gnu/krunner-version.static-gnu.txt
ai/backend/krunner/static_gnu/plugin.py
ai/backend/krunner/static_gnu/ttyd_linux.aarch64.bin
ai/backend/krunner/static_gnu/versions.txt
ai/backend/krunner/static_gnu/licenses/LICENSE.async-timeout.txt
ai/backend/krunner/static_gnu/licenses/LICENSE.attrs.txt
ai/backend/krunner/static_gnu/licenses/LICENSE.ipython-genutils.md
ai/backend/krunner/static_gnu/licenses/LICENSE.janus.txt
ai/backend/krunner/static_gnu/licenses/LICENSE.jupyter-client.md
ai/backend/krunner/static_gnu/licenses/LICENSE.jupyter-core.md
ai/backend/krunner/static_gnu/licenses/LICENSE.msgpack.txt
ai/backend/krunner/static_gnu/licenses/LICENSE.python-dateutil.txt
ai/backend/krunner/static_gnu/licenses/LICENSE.pyzmq.txt
ai/backend/krunner/static_gnu/licenses/LICENSE.six.txt
ai/backend/krunner/static_gnu/licenses/LICENSE.tornado.txt
ai/backend/krunner/static_gnu/licenses/LICENSE.traitlets.md
ai/backend/krunner/static_gnu/licenses/LICENSE.ttyd.txt
ai/backend/krunner/static_gnu/licenses/LICENSE.uvloop.txt
backend_ai_krunner_static_gnu-4.4.0.dist-info/licenses/LICENSE
backend_ai_krunner_static_gnu-4.4.0.dist-info/licenses/src/ai/backend/krunner/static_gnu/licenses/LICENSE.async-timeout.txt
backend_ai_krunner_static_gnu-4.4.0.dist-info/licenses/src/ai/backend/krunner/static_gnu/licenses/LICENSE.attrs.txt
backend_ai_krunner_static_gnu-4.4.0.dist-info/licenses/src/ai/backend/krunner/static_gnu/licenses/LICENSE.ipython-genutils.md
backend_ai_krunner_static_gnu-4.4.0.dist-info/licenses/src/ai/backend/krunner/static_gnu/licenses/LICENSE.janus.txt
backend_ai_krunner_static_gnu-4.4.0.dist-info/licenses/src/ai/backend/krunner/static_gnu/licenses/LICENSE.jupyter-client.md
backend_ai_krunner_static_gnu-4.4.0.dist-info/licenses/src/ai/backend/krunner/static_gnu/licenses/LICENSE.jupyter-core.md
backend_ai_krunner_static_gnu-4.4.0.dist-info/licenses/src/ai/backend/krunner/static_gnu/licenses/LICENSE.msgpack.txt
backend_ai_krunner_static_gnu-4.4.0.dist-info/licenses/src/ai/backend/krunner/static_gnu/licenses/LICENSE.python-dateutil.txt
backend_ai_krunner_static_gnu-4.4.0.dist-info/licenses/src/ai/backend/krunner/static_gnu/licenses/LICENSE.pyzmq.txt
backend_ai_krunner_static_gnu-4.4.0.dist-info/licenses/src/ai/backend/krunner/static_gnu/licenses/LICENSE.six.txt
backend_ai_krunner_static_gnu-4.4.0.dist-info/licenses/src/ai/backend/krunner/static_gnu/licenses/LICENSE.tornado.txt
backend_ai_krunner_static_gnu-4.4.0.dist-info/licenses/src/ai/backend/krunner/static_gnu/licenses/LICENSE.traitlets.md
backend_ai_krunner_static_gnu-4.4.0.dist-info/licenses/src/ai/backend/krunner/static_gnu/licenses/LICENSE.ttyd.txt
backend_ai_krunner_static_gnu-4.4.0.dist-info/licenses/src/ai/backend/krunner/static_gnu/licenses/LICENSE.uvloop.txt
backend_ai_krunner_static_gnu-4.4.0.dist-info/METADATA
backend_ai_krunner_static_gnu-4.4.0.dist-info/WHEEL
backend_ai_krunner_static_gnu-4.4.0.dist-info/entry_points.txt
backend_ai_krunner_static_gnu-4.4.0.dist-info/top_level.txt
backend_ai_krunner_static_gnu-4.4.0.dist-info/RECORD
