Metadata-Version: 2.4
Name: backend.ai-krunner-static-gnu
Version: 4.4.0
Summary: Backend.AI Kernel Runner based on GNU libc
Author-email: Lablup <devops@lablup.com>
Project-URL: Homepage, https://github.com/lablup/backend.ai-krunner-static-gnu
Project-URL: Issues, https://github.com/lablup/backend.ai/issues
Classifier: Programming Language :: Python :: 3
Classifier: Operating System :: OS Independent
Requires-Python: >=3.9
License-File: LICENSE
License-File: src/ai/backend/krunner/static_gnu/licenses/LICENSE.async-timeout.txt
License-File: src/ai/backend/krunner/static_gnu/licenses/LICENSE.attrs.txt
License-File: src/ai/backend/krunner/static_gnu/licenses/LICENSE.janus.txt
License-File: src/ai/backend/krunner/static_gnu/licenses/LICENSE.msgpack.txt
License-File: src/ai/backend/krunner/static_gnu/licenses/LICENSE.python-dateutil.txt
License-File: src/ai/backend/krunner/static_gnu/licenses/LICENSE.pyzmq.txt
License-File: src/ai/backend/krunner/static_gnu/licenses/LICENSE.six.txt
License-File: src/ai/backend/krunner/static_gnu/licenses/LICENSE.tornado.txt
License-File: src/ai/backend/krunner/static_gnu/licenses/LICENSE.ttyd.txt
License-File: src/ai/backend/krunner/static_gnu/licenses/LICENSE.uvloop.txt
License-File: src/ai/backend/krunner/static_gnu/licenses/LICENSE.ipython-genutils.md
License-File: src/ai/backend/krunner/static_gnu/licenses/LICENSE.jupyter-client.md
License-File: src/ai/backend/krunner/static_gnu/licenses/LICENSE.jupyter-core.md
License-File: src/ai/backend/krunner/static_gnu/licenses/LICENSE.traitlets.md
Dynamic: license-file
